README.md
setup.py
lazydl/__init__.py
lazydl/intro.py
lazydl.egg-info/PKG-INFO
lazydl.egg-info/SOURCES.txt
lazydl.egg-info/dependency_links.txt
lazydl.egg-info/requires.txt
lazydl.egg-info/top_level.txt
lazydl/utils/__init__.py
lazydl/utils/catch_error.py
lazydl/utils/data.py
lazydl/utils/dataset.py
lazydl/utils/eval_methods.py
lazydl/utils/hf_util.py
lazydl/utils/init.py
lazydl/utils/io.py
lazydl/utils/load_class.py
lazydl/utils/log.py
lazydl/utils/loss.py
lazydl/utils/model_wrapper.py
lazydl/utils/modules.py
lazydl/utils/notice.py
lazydl/utils/processing_unit.py
lazydl/utils/redis.py
lazydl/utils/result.py
lazydl/utils/tensor_util.py
lazydl/utils/tokenize.py
lazydl/utils/trainer.py