Metadata-Version: 2.1
Name: lazydl
Version: 0.2.83
Summary: Deep learning tools
Home-page: https://github.com/deng1fan
Author: deng1fan
Author-email: dengyifan@iie.ac.cn
Keywords: lazydl,deep learning,pytorch
Requires-Python: >=3.6
